examples/format_simple.py
pandiag/__init__.py
pandiag/__main__.py
pandiag/utils.py
pandiag/dot/__init__.py
pandiag/dot/format.py
pandiag/drawio/__init__.py
pandiag/drawio/parse.py
pandiag/mermaid/__init__.py
pandiag/mermaid/format.py
pandiag/model/__init__.py
pandiag/model/graph.py
pandiag-0.1.0.dist-info/LICENSE
pandiag-0.1.0.dist-info/METADATA
pandiag-0.1.0.dist-info/WHEEL
pandiag-0.1.0.dist-info/entry_points.txt
pandiag-0.1.0.dist-info/top_level.txt
pandiag-0.1.0.dist-info/RECORD
