Metadata-Version: 2.1
Name: pandiag
Version: 0.1.0
Summary: CLI tool for converting between diagram formats
License: GNU GENERAL PUBLIC LICENSE
Project-URL: Homepage, https://github.com/fwcd/pandiag
Project-URL: Repository, https://github.com/fwcd/pandiag
Keywords: document,diagram,converter
Classifier: Topic :: Multimedia :: Graphics :: Graphics Conversion
Classifier: Topic :: Utilities
Requires-Python: >=3.10
License-File: LICENSE
